immich_autotag/__init__.py
immich_autotag/__main__.py
immich_autotag/entrypoint.py
immich_autotag/types.py
immich_autotag/version.py
immich_autotag/albums/__init__.py
immich_autotag/albums/album/album_response_wrapper.py
immich_autotag/albums/albums/album_collection_wrapper.py
immich_autotag/albums/albums/album_error_entry.py
immich_autotag/albums/albums/album_list.py
immich_autotag/albums/albums/asset_to_albums_map.py
immich_autotag/albums/albums/list_albums.py
immich_autotag/albums/albums/unavailable_albums.py
immich_autotag/albums/duplicates/__init__.py
immich_autotag/albums/duplicates/collect_duplicate.py
immich_autotag/albums/duplicates/duplicate_album_reports.py
immich_autotag/albums/duplicates/merge_duplicate_albums.py
immich_autotag/albums/duplicates/mover.py
immich_autotag/albums/duplicates/write_duplicates_summary.py
immich_autotag/albums/folder_analysis/__init__.py
immich_autotag/albums/folder_analysis/album_folder_analyzer.py
immich_autotag/albums/permissions/__init__.py
immich_autotag/albums/permissions/album_policy_resolver.py
immich_autotag/assets/__init__.py
immich_autotag/assets/asset_manager.py
immich_autotag/assets/asset_response_wrapper.py
immich_autotag/assets/get_all_assets.py
immich_autotag/assets/print_asset_details.py
immich_autotag/assets/albums/__init__.py
immich_autotag/assets/albums/_process_album_detection.py
immich_autotag/assets/albums/album_decision.py
immich_autotag/assets/albums/analyze_and_assign_album.py
immich_autotag/assets/albums/temporary_manager/__init__.py
immich_autotag/assets/albums/temporary_manager/cleanup.py
immich_autotag/assets/albums/temporary_manager/create_if_missing_classification.py
immich_autotag/assets/albums/temporary_manager/health.py
immich_autotag/assets/albums/temporary_manager/naming.py
immich_autotag/assets/consistency_checks/_album_date_consistency.py
immich_autotag/assets/date_correction/__init__.py
immich_autotag/assets/date_correction/asset_date_candidate.py
immich_autotag-0.74.0.dist-info/licenses/LICENSE
immich_autotag-0.74.0.dist-info/METADATA
immich_autotag-0.74.0.dist-info/WHEEL
immich_autotag-0.74.0.dist-info/entry_points.txt
immich_autotag-0.74.0.dist-info/top_level.txt
immich_autotag-0.74.0.dist-info/RECORD
