Metadata-Version: 2.4
Name: immich-autotag
Version: 0.74.0
Summary: Immich autotagging and album management system
Author-email: txemi <txemitron@gmail.com>
License-Expression: GPL-3.0-only
Keywords: immich,autotag,photo,album,tagging,automation
Classifier: Programming Language :: Python :: 3
Classifier: Programming Language :: Python :: 3.10
Classifier: Programming Language :: Python :: 3.11
Classifier: Operating System :: OS Independent
Classifier: Intended Audience :: End Users/Desktop
Classifier: Intended Audience :: Developers
Classifier: Topic :: Multimedia :: Graphics :: Graphics Conversion
Classifier: Topic :: Utilities
License-File: LICENSE
Requires-Dist: httpx<0.29.0,>=0.23.0
Requires-Dist: attrs>=22.2.0
Requires-Dist: python-dateutil>=2.8.0
Requires-Dist: typeguard
Requires-Dist: pandas>=1.3.0
Requires-Dist: pyyaml
Requires-Dist: pydantic
Requires-Dist: certifi
Requires-Dist: idna
Requires-Dist: typing_extensions
Requires-Dist: six
Requires-Dist: urllib3
Requires-Dist: setuptools
Requires-Dist: requests
Requires-Dist: importlib-metadata; python_version < "3.8"
Requires-Dist: gitpython
Provides-Extra: dev
Requires-Dist: ruff; extra == "dev"
Requires-Dist: black; extra == "dev"
Requires-Dist: isort; extra == "dev"
Requires-Dist: flake8; extra == "dev"
Requires-Dist: mypy; extra == "dev"
Dynamic: license-file
